<?xml version = "1.0"?>

<XSPEC xmlns:xsi="http://www.w3.org/2001/XMLSchema-instance" xsi:noNamespaceSchemaLocation="xspec.xsd">
    <semanticDatabaseName></semanticDatabaseName>
    <databaseName>Instacart</databaseName>
    <databaseSystemName>Instacart</databaseSystemName>
    <databaseSchemaName></databaseSchemaName>
    <databaseId>80020202</databaseId>
    <databaseProductName>MongoDB</databaseProductName>
    <databaseProductVersion></databaseProductVersion>
    <urlJDBC>jdbc:mongo://ec2-3-137-209-245.us-east-2.compute.amazonaws.com</urlJDBC>
    <driverName>mongodb.jdbc.MongoDriver</driverName>
    <driverClass>mongodb.jdbc.MongoDriver</driverClass>
    <delimitId>"</delimitId>
    <catalogsIncluded></catalogsIncluded>
    <tablesIncluded></tablesIncluded>
    <tablesExcluded></tablesExcluded>

   <TABLE>
        <semanticTableName>denormalinstacartfact</semanticTableName>
        <tableName>"Denormalinstacartfact"</tableName>
        <schemaName>Instacart</schemaName>
        <catalogName></catalogName>
        <caseSensitive>true</caseSensitive>
        <comment></comment>
        <numTuples>1384617</numTuples>
     <FIELD>
        <semanticFieldName>_id</semanticFieldName>
        <fieldName>"_id"</fieldName>
        <dataType>12</dataType>
        <dataTypeName>varchar</dataTypeName>
        <fieldSize>24</fieldSize>
        <decimalDigits>0</decimalDigits>
        <numberRadixPrecision>24</numberRadixPrecision>
        <remarks></remarks>
        <defaultValue></defaultValue>
        <characterOctetLength>24</characterOctetLength>
        <ordinalPosition>1</ordinalPosition>
        <isNullable></isNullable>
        <numDistinctValues>0</numDistinctValues>
     </FIELD>

     <FIELD>
        <semanticFieldName>add_to_cart_order</semanticFieldName>
        <fieldName>"add_to_cart_order"</fieldName>
        <dataType>4</dataType>
        <dataTypeName>integer</dataTypeName>
        <fieldSize>10</fieldSize>
        <decimalDigits>0</decimalDigits>
        <numberRadixPrecision>10</numberRadixPrecision>
        <remarks></remarks>
        <defaultValue></defaultValue>
        <characterOctetLength>10</characterOctetLength>
        <ordinalPosition>4</ordinalPosition>
        <isNullable></isNullable>
        <numDistinctValues>0</numDistinctValues>
     </FIELD>

     <FIELD>
        <semanticFieldName>aisle</semanticFieldName>
        <fieldName>"aisle"</fieldName>
        <dataType>12</dataType>
        <dataTypeName>varchar</dataTypeName>
        <fieldSize>16793600</fieldSize>
        <decimalDigits>0</decimalDigits>
        <numberRadixPrecision>16793600</numberRadixPrecision>
        <remarks></remarks>
        <defaultValue></defaultValue>
        <characterOctetLength>16793600</characterOctetLength>
        <ordinalPosition>9</ordinalPosition>
        <isNullable></isNullable>
        <numDistinctValues>0</numDistinctValues>
     </FIELD>

     <FIELD>
        <semanticFieldName>aisle_id</semanticFieldName>
        <fieldName>"aisle_id"</fieldName>
        <dataType>4</dataType>
        <dataTypeName>integer</dataTypeName>
        <fieldSize>10</fieldSize>
        <decimalDigits>0</decimalDigits>
        <numberRadixPrecision>10</numberRadixPrecision>
        <remarks></remarks>
        <defaultValue></defaultValue>
        <characterOctetLength>10</characterOctetLength>
        <ordinalPosition>8</ordinalPosition>
        <isNullable></isNullable>
        <numDistinctValues>0</numDistinctValues>
     </FIELD>

     <FIELD>
        <semanticFieldName>days_since_prior_order</semanticFieldName>
        <fieldName>"days_since_prior_order"</fieldName>
        <dataType>4</dataType>
        <dataTypeName>integer</dataTypeName>
        <fieldSize>10</fieldSize>
        <decimalDigits>0</decimalDigits>
        <numberRadixPrecision>10</numberRadixPrecision>
        <remarks></remarks>
        <defaultValue></defaultValue>
        <characterOctetLength>10</characterOctetLength>
        <ordinalPosition>16</ordinalPosition>
        <isNullable></isNullable>
        <numDistinctValues>0</numDistinctValues>
     </FIELD>

     <FIELD>
        <semanticFieldName>department_id</semanticFieldName>
        <fieldName>"department_id"</fieldName>
        <dataType>4</dataType>
        <dataTypeName>integer</dataTypeName>
        <fieldSize>10</fieldSize>
        <decimalDigits>0</decimalDigits>
        <numberRadixPrecision>10</numberRadixPrecision>
        <remarks></remarks>
        <defaultValue></defaultValue>
        <characterOctetLength>10</characterOctetLength>
        <ordinalPosition>10</ordinalPosition>
        <isNullable></isNullable>
        <numDistinctValues>0</numDistinctValues>
     </FIELD>

     <FIELD>
        <semanticFieldName>departments</semanticFieldName>
        <fieldName>"departments"</fieldName>
        <dataType>12</dataType>
        <dataTypeName>varchar</dataTypeName>
        <fieldSize>16793600</fieldSize>
        <decimalDigits>0</decimalDigits>
        <numberRadixPrecision>16793600</numberRadixPrecision>
        <remarks></remarks>
        <defaultValue></defaultValue>
        <characterOctetLength>16793600</characterOctetLength>
        <ordinalPosition>11</ordinalPosition>
        <isNullable></isNullable>
        <numDistinctValues>0</numDistinctValues>
     </FIELD>

     <FIELD>
        <semanticFieldName>order_dow</semanticFieldName>
        <fieldName>"order_dow"</fieldName>
        <dataType>4</dataType>
        <dataTypeName>integer</dataTypeName>
        <fieldSize>10</fieldSize>
        <decimalDigits>0</decimalDigits>
        <numberRadixPrecision>10</numberRadixPrecision>
        <remarks></remarks>
        <defaultValue></defaultValue>
        <characterOctetLength>10</characterOctetLength>
        <ordinalPosition>14</ordinalPosition>
        <isNullable></isNullable>
        <numDistinctValues>0</numDistinctValues>
     </FIELD>

     <FIELD>
        <semanticFieldName>order_hour_of_day</semanticFieldName>
        <fieldName>"order_hour_of_day"</fieldName>
        <dataType>4</dataType>
        <dataTypeName>integer</dataTypeName>
        <fieldSize>10</fieldSize>
        <decimalDigits>0</decimalDigits>
        <numberRadixPrecision>10</numberRadixPrecision>
        <remarks></remarks>
        <defaultValue></defaultValue>
        <characterOctetLength>10</characterOctetLength>
        <ordinalPosition>15</ordinalPosition>
        <isNullable></isNullable>
        <numDistinctValues>0</numDistinctValues>
     </FIELD>

     <FIELD>
        <semanticFieldName>order_id</semanticFieldName>
        <fieldName>"order_id"</fieldName>
        <dataType>4</dataType>
        <dataTypeName>integer</dataTypeName>
        <fieldSize>10</fieldSize>
        <decimalDigits>0</decimalDigits>
        <numberRadixPrecision>10</numberRadixPrecision>
        <remarks></remarks>
        <defaultValue></defaultValue>
        <characterOctetLength>10</characterOctetLength>
        <ordinalPosition>2</ordinalPosition>
        <isNullable></isNullable>
        <numDistinctValues>0</numDistinctValues>
     </FIELD>

     <FIELD>
        <semanticFieldName>order_number</semanticFieldName>
        <fieldName>"order_number"</fieldName>
        <dataType>4</dataType>
        <dataTypeName>integer</dataTypeName>
        <fieldSize>10</fieldSize>
        <decimalDigits>0</decimalDigits>
        <numberRadixPrecision>10</numberRadixPrecision>
        <remarks></remarks>
        <defaultValue></defaultValue>
        <characterOctetLength>10</characterOctetLength>
        <ordinalPosition>12</ordinalPosition>
        <isNullable></isNullable>
        <numDistinctValues>0</numDistinctValues>
     </FIELD>

     <FIELD>
        <semanticFieldName>price</semanticFieldName>
        <fieldName>"price"</fieldName>
        <dataType>4</dataType>
        <dataTypeName>integer</dataTypeName>
        <fieldSize>10</fieldSize>
        <decimalDigits>0</decimalDigits>
        <numberRadixPrecision>10</numberRadixPrecision>
        <remarks></remarks>
        <defaultValue></defaultValue>
        <characterOctetLength>10</characterOctetLength>
        <ordinalPosition>5</ordinalPosition>
        <isNullable></isNullable>
        <numDistinctValues>0</numDistinctValues>
     </FIELD>

     <FIELD>
        <semanticFieldName>product_id</semanticFieldName>
        <fieldName>"product_id"</fieldName>
        <dataType>4</dataType>
        <dataTypeName>integer</dataTypeName>
        <fieldSize>10</fieldSize>
        <decimalDigits>0</decimalDigits>
        <numberRadixPrecision>10</numberRadixPrecision>
        <remarks></remarks>
        <defaultValue></defaultValue>
        <characterOctetLength>10</characterOctetLength>
        <ordinalPosition>3</ordinalPosition>
        <isNullable></isNullable>
        <numDistinctValues>0</numDistinctValues>
     </FIELD>

     <FIELD>
        <semanticFieldName>product_name</semanticFieldName>
        <fieldName>"product_name"</fieldName>
        <dataType>12</dataType>
        <dataTypeName>varchar</dataTypeName>
        <fieldSize>16793600</fieldSize>
        <decimalDigits>0</decimalDigits>
        <numberRadixPrecision>16793600</numberRadixPrecision>
        <remarks></remarks>
        <defaultValue></defaultValue>
        <characterOctetLength>16793600</characterOctetLength>
        <ordinalPosition>7</ordinalPosition>
        <isNullable></isNullable>
        <numDistinctValues>0</numDistinctValues>
     </FIELD>

     <FIELD>
        <semanticFieldName>reordered</semanticFieldName>
        <fieldName>"reordered"</fieldName>
        <dataType>4</dataType>
        <dataTypeName>integer</dataTypeName>
        <fieldSize>10</fieldSize>
        <decimalDigits>0</decimalDigits>
        <numberRadixPrecision>10</numberRadixPrecision>
        <remarks></remarks>
        <defaultValue></defaultValue>
        <characterOctetLength>10</characterOctetLength>
        <ordinalPosition>6</ordinalPosition>
        <isNullable></isNullable>
        <numDistinctValues>0</numDistinctValues>
     </FIELD>

     <FIELD>
        <semanticFieldName>user_id</semanticFieldName>
        <fieldName>"user_id"</fieldName>
        <dataType>4</dataType>
        <dataTypeName>integer</dataTypeName>
        <fieldSize>10</fieldSize>
        <decimalDigits>0</decimalDigits>
        <numberRadixPrecision>10</numberRadixPrecision>
        <remarks></remarks>
        <defaultValue></defaultValue>
        <characterOctetLength>10</characterOctetLength>
        <ordinalPosition>13</ordinalPosition>
        <isNullable></isNullable>
        <numDistinctValues>0</numDistinctValues>
     </FIELD>

     <PRIMARYKEY>
        <keyName>pk_Denormalinstacartfact</keyName>
        <keyType>1</keyType>
        <FIELDS>
        <fieldName>"_id"</fieldName>
        </FIELDS>
     </PRIMARYKEY>

   </TABLE>

   <TABLE>
        <semanticTableName>aisles</semanticTableName>
        <tableName>"aisles"</tableName>
        <schemaName>Instacart</schemaName>
        <catalogName></catalogName>
        <caseSensitive>true</caseSensitive>
        <comment></comment>
        <numTuples>134</numTuples>
     <FIELD>
        <semanticFieldName>_id</semanticFieldName>
        <fieldName>"_id"</fieldName>
        <dataType>12</dataType>
        <dataTypeName>varchar</dataTypeName>
        <fieldSize>24</fieldSize>
        <decimalDigits>0</decimalDigits>
        <numberRadixPrecision>24</numberRadixPrecision>
        <remarks></remarks>
        <defaultValue></defaultValue>
        <characterOctetLength>24</characterOctetLength>
        <ordinalPosition>1</ordinalPosition>
        <isNullable></isNullable>
        <numDistinctValues>0</numDistinctValues>
     </FIELD>

     <FIELD>
        <semanticFieldName>aisle</semanticFieldName>
        <fieldName>"aisle"</fieldName>
        <dataType>12</dataType>
        <dataTypeName>varchar</dataTypeName>
        <fieldSize>16793600</fieldSize>
        <decimalDigits>0</decimalDigits>
        <numberRadixPrecision>16793600</numberRadixPrecision>
        <remarks></remarks>
        <defaultValue></defaultValue>
        <characterOctetLength>16793600</characterOctetLength>
        <ordinalPosition>3</ordinalPosition>
        <isNullable></isNullable>
        <numDistinctValues>0</numDistinctValues>
     </FIELD>

     <FIELD>
        <semanticFieldName>aisle_id</semanticFieldName>
        <fieldName>"aisle_id"</fieldName>
        <dataType>12</dataType>
        <dataTypeName>varchar</dataTypeName>
        <fieldSize>16793600</fieldSize>
        <decimalDigits>0</decimalDigits>
        <numberRadixPrecision>16793600</numberRadixPrecision>
        <remarks></remarks>
        <defaultValue></defaultValue>
        <characterOctetLength>16793600</characterOctetLength>
        <ordinalPosition>2</ordinalPosition>
        <isNullable></isNullable>
        <numDistinctValues>0</numDistinctValues>
     </FIELD>

     <FIELD>
        <semanticFieldName>department_id</semanticFieldName>
        <fieldName>"department_id"</fieldName>
        <dataType>12</dataType>
        <dataTypeName>varchar</dataTypeName>
        <fieldSize>16793600</fieldSize>
        <decimalDigits>0</decimalDigits>
        <numberRadixPrecision>16793600</numberRadixPrecision>
        <remarks></remarks>
        <defaultValue></defaultValue>
        <characterOctetLength>16793600</characterOctetLength>
        <ordinalPosition>4</ordinalPosition>
        <isNullable></isNullable>
        <numDistinctValues>0</numDistinctValues>
     </FIELD>

     <PRIMARYKEY>
        <keyName>pk_aisles</keyName>
        <keyType>1</keyType>
        <FIELDS>
        <fieldName>"_id"</fieldName>
        </FIELDS>
     </PRIMARYKEY>

   </TABLE>

   <TABLE>
        <semanticTableName>departments</semanticTableName>
        <tableName>"departments"</tableName>
        <schemaName>Instacart</schemaName>
        <catalogName></catalogName>
        <caseSensitive>true</caseSensitive>
        <comment></comment>
        <numTuples>21</numTuples>
     <FIELD>
        <semanticFieldName>_id</semanticFieldName>
        <fieldName>"_id"</fieldName>
        <dataType>12</dataType>
        <dataTypeName>varchar</dataTypeName>
        <fieldSize>24</fieldSize>
        <decimalDigits>0</decimalDigits>
        <numberRadixPrecision>24</numberRadixPrecision>
        <remarks></remarks>
        <defaultValue></defaultValue>
        <characterOctetLength>24</characterOctetLength>
        <ordinalPosition>1</ordinalPosition>
        <isNullable></isNullable>
        <numDistinctValues>0</numDistinctValues>
     </FIELD>

     <FIELD>
        <semanticFieldName>department_id</semanticFieldName>
        <fieldName>"department_id"</fieldName>
        <dataType>12</dataType>
        <dataTypeName>varchar</dataTypeName>
        <fieldSize>16793600</fieldSize>
        <decimalDigits>0</decimalDigits>
        <numberRadixPrecision>16793600</numberRadixPrecision>
        <remarks></remarks>
        <defaultValue></defaultValue>
        <characterOctetLength>16793600</characterOctetLength>
        <ordinalPosition>2</ordinalPosition>
        <isNullable></isNullable>
        <numDistinctValues>0</numDistinctValues>
     </FIELD>

     <FIELD>
        <semanticFieldName>departments</semanticFieldName>
        <fieldName>"departments"</fieldName>
        <dataType>12</dataType>
        <dataTypeName>varchar</dataTypeName>
        <fieldSize>16793600</fieldSize>
        <decimalDigits>0</decimalDigits>
        <numberRadixPrecision>16793600</numberRadixPrecision>
        <remarks></remarks>
        <defaultValue></defaultValue>
        <characterOctetLength>16793600</characterOctetLength>
        <ordinalPosition>3</ordinalPosition>
        <isNullable></isNullable>
        <numDistinctValues>0</numDistinctValues>
     </FIELD>

     <PRIMARYKEY>
        <keyName>pk_departments</keyName>
        <keyType>1</keyType>
        <FIELDS>
        <fieldName>"_id"</fieldName>
        </FIELDS>
     </PRIMARYKEY>

   </TABLE>

   <TABLE>
        <semanticTableName>order_products</semanticTableName>
        <tableName>"order_products"</tableName>
        <schemaName>Instacart</schemaName>
        <catalogName></catalogName>
        <caseSensitive>true</caseSensitive>
        <comment></comment>
        <numTuples>1048575</numTuples>
     <FIELD>
        <semanticFieldName>_id</semanticFieldName>
        <fieldName>"_id"</fieldName>
        <dataType>12</dataType>
        <dataTypeName>varchar</dataTypeName>
        <fieldSize>24</fieldSize>
        <decimalDigits>0</decimalDigits>
        <numberRadixPrecision>24</numberRadixPrecision>
        <remarks></remarks>
        <defaultValue></defaultValue>
        <characterOctetLength>24</characterOctetLength>
        <ordinalPosition>1</ordinalPosition>
        <isNullable></isNullable>
        <numDistinctValues>0</numDistinctValues>
     </FIELD>

     <FIELD>
        <semanticFieldName>add_to_cart_order</semanticFieldName>
        <fieldName>"add_to_cart_order"</fieldName>
        <dataType>12</dataType>
        <dataTypeName>varchar</dataTypeName>
        <fieldSize>16793600</fieldSize>
        <decimalDigits>0</decimalDigits>
        <numberRadixPrecision>16793600</numberRadixPrecision>
        <remarks></remarks>
        <defaultValue></defaultValue>
        <characterOctetLength>16793600</characterOctetLength>
        <ordinalPosition>5</ordinalPosition>
        <isNullable></isNullable>
        <numDistinctValues>0</numDistinctValues>
     </FIELD>

     <FIELD>
        <semanticFieldName>order_id</semanticFieldName>
        <fieldName>"order_id"</fieldName>
        <dataType>12</dataType>
        <dataTypeName>varchar</dataTypeName>
        <fieldSize>16793600</fieldSize>
        <decimalDigits>0</decimalDigits>
        <numberRadixPrecision>16793600</numberRadixPrecision>
        <remarks></remarks>
        <defaultValue></defaultValue>
        <characterOctetLength>16793600</characterOctetLength>
        <ordinalPosition>2</ordinalPosition>
        <isNullable></isNullable>
        <numDistinctValues>0</numDistinctValues>
     </FIELD>

     <FIELD>
        <semanticFieldName>price</semanticFieldName>
        <fieldName>"price"</fieldName>
        <dataType>99999</dataType>
        <dataTypeName>(unknown)</dataTypeName>
        <fieldSize>16793600</fieldSize>
        <decimalDigits>0</decimalDigits>
        <numberRadixPrecision>16793600</numberRadixPrecision>
        <remarks></remarks>
        <defaultValue></defaultValue>
        <characterOctetLength>16793600</characterOctetLength>
        <ordinalPosition>6</ordinalPosition>
        <isNullable></isNullable>
        <numDistinctValues>0</numDistinctValues>
     </FIELD>

     <FIELD>
        <semanticFieldName>product_id</semanticFieldName>
        <fieldName>"product_id"</fieldName>
        <dataType>12</dataType>
        <dataTypeName>varchar</dataTypeName>
        <fieldSize>16793600</fieldSize>
        <decimalDigits>0</decimalDigits>
        <numberRadixPrecision>16793600</numberRadixPrecision>
        <remarks></remarks>
        <defaultValue></defaultValue>
        <characterOctetLength>16793600</characterOctetLength>
        <ordinalPosition>3</ordinalPosition>
        <isNullable></isNullable>
        <numDistinctValues>0</numDistinctValues>
     </FIELD>

     <FIELD>
        <semanticFieldName>reordered</semanticFieldName>
        <fieldName>"reordered"</fieldName>
        <dataType>12</dataType>
        <dataTypeName>varchar</dataTypeName>
        <fieldSize>16793600</fieldSize>
        <decimalDigits>0</decimalDigits>
        <numberRadixPrecision>16793600</numberRadixPrecision>
        <remarks></remarks>
        <defaultValue></defaultValue>
        <characterOctetLength>16793600</characterOctetLength>
        <ordinalPosition>4</ordinalPosition>
        <isNullable></isNullable>
        <numDistinctValues>0</numDistinctValues>
     </FIELD>

     <PRIMARYKEY>
        <keyName>pk_order_products</keyName>
        <keyType>1</keyType>
        <FIELDS>
        <fieldName>"_id"</fieldName>
        </FIELDS>
     </PRIMARYKEY>

   </TABLE>

   <TABLE>
        <semanticTableName>orders</semanticTableName>
        <tableName>"orders"</tableName>
        <schemaName>Instacart</schemaName>
        <catalogName></catalogName>
        <caseSensitive>true</caseSensitive>
        <comment></comment>
        <numTuples>1048575</numTuples>
     <FIELD>
        <semanticFieldName>_id</semanticFieldName>
        <fieldName>"_id"</fieldName>
        <dataType>12</dataType>
        <dataTypeName>varchar</dataTypeName>
        <fieldSize>24</fieldSize>
        <decimalDigits>0</decimalDigits>
        <numberRadixPrecision>24</numberRadixPrecision>
        <remarks></remarks>
        <defaultValue></defaultValue>
        <characterOctetLength>24</characterOctetLength>
        <ordinalPosition>1</ordinalPosition>
        <isNullable></isNullable>
        <numDistinctValues>0</numDistinctValues>
     </FIELD>

     <FIELD>
        <semanticFieldName>add_to_cart_order</semanticFieldName>
        <fieldName>"add_to_cart_order"</fieldName>
        <dataType>12</dataType>
        <dataTypeName>varchar</dataTypeName>
        <fieldSize>16793600</fieldSize>
        <decimalDigits>0</decimalDigits>
        <numberRadixPrecision>16793600</numberRadixPrecision>
        <remarks></remarks>
        <defaultValue></defaultValue>
        <characterOctetLength>16793600</characterOctetLength>
        <ordinalPosition>5</ordinalPosition>
        <isNullable></isNullable>
        <numDistinctValues>0</numDistinctValues>
     </FIELD>

     <FIELD>
        <semanticFieldName>order_id</semanticFieldName>
        <fieldName>"order_id"</fieldName>
        <dataType>12</dataType>
        <dataTypeName>varchar</dataTypeName>
        <fieldSize>16793600</fieldSize>
        <decimalDigits>0</decimalDigits>
        <numberRadixPrecision>16793600</numberRadixPrecision>
        <remarks></remarks>
        <defaultValue></defaultValue>
        <characterOctetLength>16793600</characterOctetLength>
        <ordinalPosition>2</ordinalPosition>
        <isNullable></isNullable>
        <numDistinctValues>0</numDistinctValues>
     </FIELD>

     <FIELD>
        <semanticFieldName>price</semanticFieldName>
        <fieldName>"price"</fieldName>
        <dataType>99999</dataType>
        <dataTypeName>(unknown)</dataTypeName>
        <fieldSize>16793600</fieldSize>
        <decimalDigits>0</decimalDigits>
        <numberRadixPrecision>16793600</numberRadixPrecision>
        <remarks></remarks>
        <defaultValue></defaultValue>
        <characterOctetLength>16793600</characterOctetLength>
        <ordinalPosition>6</ordinalPosition>
        <isNullable></isNullable>
        <numDistinctValues>0</numDistinctValues>
     </FIELD>

     <FIELD>
        <semanticFieldName>product_id</semanticFieldName>
        <fieldName>"product_id"</fieldName>
        <dataType>12</dataType>
        <dataTypeName>varchar</dataTypeName>
        <fieldSize>16793600</fieldSize>
        <decimalDigits>0</decimalDigits>
        <numberRadixPrecision>16793600</numberRadixPrecision>
        <remarks></remarks>
        <defaultValue></defaultValue>
        <characterOctetLength>16793600</characterOctetLength>
        <ordinalPosition>3</ordinalPosition>
        <isNullable></isNullable>
        <numDistinctValues>0</numDistinctValues>
     </FIELD>

     <FIELD>
        <semanticFieldName>reordered</semanticFieldName>
        <fieldName>"reordered"</fieldName>
        <dataType>12</dataType>
        <dataTypeName>varchar</dataTypeName>
        <fieldSize>16793600</fieldSize>
        <decimalDigits>0</decimalDigits>
        <numberRadixPrecision>16793600</numberRadixPrecision>
        <remarks></remarks>
        <defaultValue></defaultValue>
        <characterOctetLength>16793600</characterOctetLength>
        <ordinalPosition>4</ordinalPosition>
        <isNullable></isNullable>
        <numDistinctValues>0</numDistinctValues>
     </FIELD>

     <PRIMARYKEY>
        <keyName>pk_orders</keyName>
        <keyType>1</keyType>
        <FIELDS>
        <fieldName>"_id"</fieldName>
        </FIELDS>
     </PRIMARYKEY>

   </TABLE>

   <TABLE>
        <semanticTableName>products</semanticTableName>
        <tableName>"products"</tableName>
        <schemaName>Instacart</schemaName>
        <catalogName></catalogName>
        <caseSensitive>true</caseSensitive>
        <comment></comment>
        <numTuples>49688</numTuples>
     <FIELD>
        <semanticFieldName>_id</semanticFieldName>
        <fieldName>"_id"</fieldName>
        <dataType>12</dataType>
        <dataTypeName>varchar</dataTypeName>
        <fieldSize>24</fieldSize>
        <decimalDigits>0</decimalDigits>
        <numberRadixPrecision>24</numberRadixPrecision>
        <remarks></remarks>
        <defaultValue></defaultValue>
        <characterOctetLength>24</characterOctetLength>
        <ordinalPosition>1</ordinalPosition>
        <isNullable></isNullable>
        <numDistinctValues>0</numDistinctValues>
     </FIELD>

     <FIELD>
        <semanticFieldName>aisle_id</semanticFieldName>
        <fieldName>"aisle_id"</fieldName>
        <dataType>12</dataType>
        <dataTypeName>varchar</dataTypeName>
        <fieldSize>16793600</fieldSize>
        <decimalDigits>0</decimalDigits>
        <numberRadixPrecision>16793600</numberRadixPrecision>
        <remarks></remarks>
        <defaultValue></defaultValue>
        <characterOctetLength>16793600</characterOctetLength>
        <ordinalPosition>4</ordinalPosition>
        <isNullable></isNullable>
        <numDistinctValues>0</numDistinctValues>
     </FIELD>

     <FIELD>
        <semanticFieldName>price</semanticFieldName>
        <fieldName>"price"</fieldName>
        <dataType>99999</dataType>
        <dataTypeName>(unknown)</dataTypeName>
        <fieldSize>16793600</fieldSize>
        <decimalDigits>0</decimalDigits>
        <numberRadixPrecision>16793600</numberRadixPrecision>
        <remarks></remarks>
        <defaultValue></defaultValue>
        <characterOctetLength>16793600</characterOctetLength>
        <ordinalPosition>5</ordinalPosition>
        <isNullable></isNullable>
        <numDistinctValues>0</numDistinctValues>
     </FIELD>

     <FIELD>
        <semanticFieldName>product_id</semanticFieldName>
        <fieldName>"product_id"</fieldName>
        <dataType>12</dataType>
        <dataTypeName>varchar</dataTypeName>
        <fieldSize>16793600</fieldSize>
        <decimalDigits>0</decimalDigits>
        <numberRadixPrecision>16793600</numberRadixPrecision>
        <remarks></remarks>
        <defaultValue></defaultValue>
        <characterOctetLength>16793600</characterOctetLength>
        <ordinalPosition>2</ordinalPosition>
        <isNullable></isNullable>
        <numDistinctValues>0</numDistinctValues>
     </FIELD>

     <FIELD>
        <semanticFieldName>product_name</semanticFieldName>
        <fieldName>"product_name"</fieldName>
        <dataType>12</dataType>
        <dataTypeName>varchar</dataTypeName>
        <fieldSize>16793600</fieldSize>
        <decimalDigits>0</decimalDigits>
        <numberRadixPrecision>16793600</numberRadixPrecision>
        <remarks></remarks>
        <defaultValue></defaultValue>
        <characterOctetLength>16793600</characterOctetLength>
        <ordinalPosition>3</ordinalPosition>
        <isNullable></isNullable>
        <numDistinctValues>0</numDistinctValues>
     </FIELD>

     <PRIMARYKEY>
        <keyName>pk_products</keyName>
        <keyType>1</keyType>
        <FIELDS>
        <fieldName>"_id"</fieldName>
        </FIELDS>
     </PRIMARYKEY>

   </TABLE>

   <TABLE>
        <semanticTableName>users</semanticTableName>
        <tableName>"users"</tableName>
        <schemaName>Instacart</schemaName>
        <catalogName></catalogName>
        <caseSensitive>true</caseSensitive>
        <comment></comment>
        <numTuples>206209</numTuples>
     <FIELD>
        <semanticFieldName>_id</semanticFieldName>
        <fieldName>"_id"</fieldName>
        <dataType>12</dataType>
        <dataTypeName>varchar</dataTypeName>
        <fieldSize>24</fieldSize>
        <decimalDigits>0</decimalDigits>
        <numberRadixPrecision>24</numberRadixPrecision>
        <remarks></remarks>
        <defaultValue></defaultValue>
        <characterOctetLength>24</characterOctetLength>
        <ordinalPosition>1</ordinalPosition>
        <isNullable></isNullable>
        <numDistinctValues>0</numDistinctValues>
     </FIELD>

     <FIELD>
        <semanticFieldName>user_id</semanticFieldName>
        <fieldName>"user_id"</fieldName>
        <dataType>12</dataType>
        <dataTypeName>varchar</dataTypeName>
        <fieldSize>16793600</fieldSize>
        <decimalDigits>0</decimalDigits>
        <numberRadixPrecision>16793600</numberRadixPrecision>
        <remarks></remarks>
        <defaultValue></defaultValue>
        <characterOctetLength>16793600</characterOctetLength>
        <ordinalPosition>2</ordinalPosition>
        <isNullable></isNullable>
        <numDistinctValues>0</numDistinctValues>
     </FIELD>

     <PRIMARYKEY>
        <keyName>pk_users</keyName>
        <keyType>1</keyType>
        <FIELDS>
        <fieldName>"_id"</fieldName>
        </FIELDS>
     </PRIMARYKEY>

   </TABLE>

</XSPEC>
